{
    "type": "FeatureCollection",
    "features": [
        {
            "type": "Feature",
            "properties": {},
            "geometry": {
                "type": "LineString",
                "coordinates": [
                    [
                        -97.52464234828949,
                        35.467328631242275
                    ],
                    [
                        -97.52472281455994,
                        35.46736358348727
                    ],
                    [
                        -97.52478182315826,
                        35.467367952516845
                    ],
                    [
                        -97.52487301826477,
                        35.46737669057525
                    ],
                    [
                        -97.5249320268631,
                        35.467367952516845
                    ],
                    [
                        -97.5249856710434,
                        35.467354845427444
                    ],
                    [
                        -97.52505540847777,
                        35.467341738335925
                    ],
                    [
                        -97.52511978149414,
                        35.46729367898208
                    ],
                    [
                        -97.52516806125641,
                        35.46723688152686
                    ],
                    [
                        -97.52520024776459,
                        35.467153869789364
                    ],
                    [
                        -97.52522706985474,
                        35.46710144127944
                    ],
                    [
                        -97.52524316310883,
                        35.46704464368844
                    ],
                    [
                        -97.52524316310883,
                        35.467009691304845
                    ],
                    [
                        -97.5252592563629,
                        35.466952893649065
                    ],
                    [
                        -97.5252592563629,
                        35.46689172689796
                    ],
                    [
                        -97.52523779869078,
                        35.46683492915888
                    ],
                    [
                        -97.52521634101868,
                        35.46676065513184
                    ],
                    [
                        -97.52518951892853,
                        35.46669948823454
                    ],
                    [
                        -97.52515196800232,
                        35.46665579756514
                    ],
                    [
                        -97.52510368824005,
                        35.46662084501254
                    ],
                    [
                        -97.52502858638763,
                        35.46658152337269
                    ],
                    [
                        -97.52496421337128,
                        35.466564047082144
                    ],
                    [
                        -97.52487301826477,
                        35.46656841615512
                    ],
                    [
                        -97.5247871875763,
                        35.46658152337269
                    ],
                    [
                        -97.52470135688782,
                        35.46660773780139
                    ],
                    [
                        -97.52461016178131,
                        35.46664705942842
                    ],
                    [
                        -97.52457797527313,
                        35.46670822636559
                    ],
                    [
                        -97.52454042434692,
                        35.46676065513184
                    ]
                ]
            }
        },
        {
            "type": "Feature",
            "properties": {},
            "geometry": {
                "type": "LineString",
                "coordinates": [
                    [
                        -97.52599954605103,
                        35.46700532225581
                    ],
                    [
                        -97.52599954605103,
                        35.46714513170676
                    ],
                    [
                        -97.52602100372314,
                        35.4672543576712
                    ],
                    [
                        -97.52610683441162,
                        35.46731115511406
                    ],
                    [
                        -97.52620339393616,
                        35.46733736930496
                    ],
                    [
                        -97.52636432647705,
                        35.46731989317865
                    ],
                    [
                        -97.52645015716553,
                        35.467276202846286
                    ],
                    [
                        -97.52652525901794,
                        35.467223774416105
                    ],
                    [
                        -97.52655744552612,
                        35.467153869789364
                    ],
                    [
                        -97.52655744552612,
                        35.467066488920494
                    ],
                    [
                        -97.52655744552612,
                        35.46697036985511
                    ],
                    [
                        -97.52656817436217,
                        35.46685677444788
                    ],
                    [
                        -97.52656817436217,
                        35.46676939325623
                    ],
                    [
                        -97.52654671669005,
                        35.46665579756514
                    ],
                    [
                        -97.52651453018188,
                        35.46656841615512
                    ],
                    [
                        -97.52643942832947,
                        35.466515987263556
                    ],
                    [
                        -97.52638041973114,
                        35.4665028800353
                    ],
                    [
                        -97.52632141113281,
                        35.46649195734347
                    ],
                    [
                        -97.52625972032547,
                        35.46649195734347
                    ],
                    [
                        -97.52618730068207,
                        35.46649851095876
                    ],
                    [
                        -97.52611756324768,
                        35.466515987263556
                    ],
                    [
                        -97.52605319023132,
                        35.4665422017136
                    ],
                    [
                        -97.5260317325592,
                        35.46663832129075
                    ],
                    [
                        -97.52598881721497,
                        35.46676939325623
                    ],
                    [
                        -97.525994181633,
                        35.46691575669858
                    ],
                    [
                        -97.52599954605103,
                        35.467009691304845
                    ]
                ]
            }
        },
        {
            "type": "Feature",
            "properties": {},
            "geometry": {
                "type": "LineString",
                "coordinates": [
                    [
                        -97.52583861351013,
                        35.46732426221056
                    ],
                    [
                        -97.52581983804703,
                        35.46648540372765
                    ]
                ]
            }
        },
        {
            "type": "Feature",
            "properties": {},
            "geometry": {
                "type": "LineString",
                "coordinates": [
                    [
                        -97.52582788467407,
                        35.466928863859536
                    ],
                    [
                        -97.5254201889038,
                        35.46731115511406
                    ]
                ]
            }
        },
        {
            "type": "Feature",
            "properties": {},
            "geometry": {
                "type": "LineString",
                "coordinates": [
                    [
                        -97.5258332490921,
                        35.466928863859536
                    ],
                    [
                        -97.5253638625145,
                        35.46648321918894
                    ]
                ]
            }
        },
        {
            "type": "Feature",
            "properties": {},
            "geometry": {
                "type": "LineString",
                "coordinates": [
                    [
                        -97.52402409911156,
                        35.46643843613208
                    ],
                    [
                        -97.52403751015663,
                        35.46705119725869
                    ],
                    [
                        -97.52401739358902,
                        35.46706976570479
                    ],
                    [
                        -97.52398923039435,
                        35.46707850379562
                    ],
                    [
                        -97.52395302057266,
                        35.46708287284066
                    ],
                    [
                        -97.5239235162735,
                        35.467083965101864
                    ],
                    [
                        -97.52387523651123,
                        35.467083965101864
                    ],
                    [
                        -97.52384170889854,
                        35.4670795960569
                    ],
                    [
                        -97.5238148868084,
                        35.467071950227584
                    ],
                    [
                        -97.52378135919571,
                        35.467061027613056
                    ],
                    [
                        -97.52375319600105,
                        35.467042459164915
                    ],
                    [
                        -97.52373307943344,
                        35.467023890712525
                    ],
                    [
                        -97.52371296286583,
                        35.467004229993535
                    ],
                    [
                        -97.52370223402977,
                        35.46698784605737
                    ],
                    [
                        -97.52369284629822,
                        35.466969277592334
                    ],
                    [
                        -97.52368345856667,
                        35.46695180138605
                    ],
                    [
                        -97.5236713886261,
                        35.46692667933286
                    ],
                    [
                        -97.52366602420805,
                        35.466897188216905
                    ],
                    [
                        -97.52366468310356,
                        35.46687643520293
                    ]
                ]
            }
        },
        {
            "type": "Feature",
            "properties": {},
            "geometry": {
                "type": "LineString",
                "coordinates": [
                    [
                        -97.52347022294998,
                        35.46739416668919
                    ],
                    [
                        -97.523472905159,
                        35.466432974781966
                    ],
                    [
                        -97.52343535423279,
                        35.466432974781966
                    ],
                    [
                        -97.52339243888855,
                        35.466432974781966
                    ],
                    [
                        -97.52338171005249,
                        35.466432974781966
                    ],
                    [
                        -97.52336561679839,
                        35.466432974781966
                    ],
                    [
                        -97.52333611249924,
                        35.466439528402034
                    ],
                    [
                        -97.52328246831894,
                        35.46644826656133
                    ],
                    [
                        -97.52324759960175,
                        35.46646792741624
                    ],
                    [
                        -97.5232046842575,
                        35.46649414188196
                    ],
                    [
                        -97.52317517995834,
                        35.4665269099521
                    ],
                    [
                        -97.52314567565918,
                        35.46655530893544
                    ],
                    [
                        -97.52313494682312,
                        35.46660118419501
                    ],
                    [
                        -97.52313494682312,
                        35.46665579756514
                    ],
                    [
                        -97.52313762903214,
                        35.46668856556943
                    ],
                    [
                        -97.52314433455466,
                        35.4667202412942
                    ],
                    [
                        -97.52315238118172,
                        35.46674208661437
                    ],
                    [
                        -97.52316176891327,
                        35.466766116459695
                    ],
                    [
                        -97.52318456768988,
                        35.46681089933409
                    ],
                    [
                        -97.5232221186161,
                        35.46686769709017
                    ],
                    [
                        -97.52324759960175,
                        35.46689500368939
                    ],
                    [
                        -97.523293197155,
                        35.4669212180159
                    ],
                    [
                        -97.52333745360374,
                        35.46693978649203
                    ],
                    [
                        -97.52338841557503,
                        35.46694852459695
                    ],
                    [
                        -97.5234380364418,
                        35.46695070912305
                    ],
                    [
                        -97.523472905159,
                        35.466931048386144
                    ]
                ]
            }
        }
    ]
}
